pygamepopup/__init__.py
pygamepopup/configuration.py
pygamepopup/constants.py
pygamepopup/fonts.py
pygamepopup/initialization.py
pygamepopup/menu_manager.py
pygamepopup/types.py
pygamepopup/_exceptions/__init__.py
pygamepopup/_exceptions/wrong_initialization_exception.py
pygamepopup/components/__init__.py
pygamepopup/components/box_element.py
pygamepopup/components/button.py
pygamepopup/components/dynamic_button.py
pygamepopup/components/image_button.py
pygamepopup/components/info_box.py
pygamepopup/components/text_element.py
pygamepopup/images/default_box.png
pygamepopup/images/default_box_hover.png
pygame_popup-0.10.0.dist-info/LICENSE
pygame_popup-0.10.0.dist-info/METADATA
pygame_popup-0.10.0.dist-info/WHEEL
pygame_popup-0.10.0.dist-info/top_level.txt
pygame_popup-0.10.0.dist-info/RECORD
