Metadata-Version: 2.1
Name: pygame-popup
Version: 0.10.0
Summary: A popup manager for pygame
Home-page: https://github.com/Grimmys/pygame_popup_manager
Author: Grimmys
Author-email: grimmys.programming@gmail.com
License: UNKNOWN
Project-URL: Issue Tracker, https://github.com/Grimmys/pygame_popup_manager/issues
Platform: UNKNOWN
Classifier: Programming Language :: Python :: 3
Classifier: License :: OSI Approved :: GNU General Public License (GPL)
Classifier: Operating System :: OS Independent
Requires-Python: >=3.7
License-File: LICENSE
Requires-Dist: pygame-ce >=2.0.0
